mlagents_envs/__init__.py
mlagents_envs/base_env.py
mlagents_envs/communicator.py
mlagents_envs/env_utils.py
mlagents_envs/environment.py
mlagents_envs/exception.py
mlagents_envs/logging_util.py
mlagents_envs/mock_communicator.py
mlagents_envs/rpc_communicator.py
mlagents_envs/rpc_utils.py
mlagents_envs/timers.py
mlagents_envs/communicator_objects/__init__.py
mlagents_envs/communicator_objects/agent_action_pb2.py
mlagents_envs/communicator_objects/agent_info_action_pair_pb2.py
mlagents_envs/communicator_objects/agent_info_pb2.py
mlagents_envs/communicator_objects/brain_parameters_pb2.py
mlagents_envs/communicator_objects/capabilities_pb2.py
mlagents_envs/communicator_objects/command_pb2.py
mlagents_envs/communicator_objects/custom_reset_parameters_pb2.py
mlagents_envs/communicator_objects/demonstration_meta_pb2.py
mlagents_envs/communicator_objects/engine_configuration_pb2.py
mlagents_envs/communicator_objects/header_pb2.py
mlagents_envs/communicator_objects/observation_pb2.py
mlagents_envs/communicator_objects/space_type_pb2.py
mlagents_envs/communicator_objects/training_analytics_pb2.py
mlagents_envs/communicator_objects/unity_input_pb2.py
mlagents_envs/communicator_objects/unity_message_pb2.py
mlagents_envs/communicator_objects/unity_output_pb2.py
mlagents_envs/communicator_objects/unity_rl_initialization_input_pb2.py
mlagents_envs/communicator_objects/unity_rl_initialization_output_pb2.py
mlagents_envs/communicator_objects/unity_rl_input_pb2.py
mlagents_envs/communicator_objects/unity_rl_output_pb2.py
mlagents_envs/communicator_objects/unity_to_external_pb2.py
mlagents_envs/communicator_objects/unity_to_external_pb2_grpc.py
mlagents_envs/registry/__init__.py
mlagents_envs/registry/base_registry_entry.py
mlagents_envs/registry/binary_utils.py
mlagents_envs/registry/remote_registry_entry.py
mlagents_envs/registry/unity_env_registry.py
mlagents_envs/side_channel/__init__.py
mlagents_envs/side_channel/engine_configuration_channel.py
navsim_mlagents_envs-0.27.0.dist-info/METADATA
navsim_mlagents_envs-0.27.0.dist-info/WHEEL
navsim_mlagents_envs-0.27.0.dist-info/top_level.txt
navsim_mlagents_envs-0.27.0.dist-info/RECORD
