Metadata-Version: 2.1
Name: navsim-mlagents-envs
Version: 0.27.0
Summary: NavSim cusomized Unity Machine Learning Agents Interface
Home-page: UNKNOWN
Author: STTC, UCF
Author-email: armando@ucf.edu
License: UNKNOWN
Platform: UNKNOWN
Classifier: Intended Audience :: Developers
Classifier: Topic :: Scientific/Engineering :: Artificial Intelligence
Classifier: License :: OSI Approved :: Apache Software License
Classifier: Programming Language :: Python :: 3.6
Classifier: Programming Language :: Python :: 3.7
Classifier: Programming Language :: Python :: 3.8
Requires-Python: >=3.6.1
Requires-Dist: cloudpickle
Requires-Dist: grpcio (>=1.11.0)
Requires-Dist: numpy (>=1.14.1)
Requires-Dist: Pillow (>=4.2.1)
Requires-Dist: protobuf (>=3.6)
Requires-Dist: pyyaml (>=3.1.0)
